{
    "st1": {
        "id": 1,
        "name": "Aisén del General Carlos Ibáñez del Campo",
        "shortname": "XI",
        "link": "",
        "comment": "",
        "image": "",
        "color_map": "#7798bb",
        "color_map_over": "#366CA3"
    },
    "st2": {
        "id": 2,
        "name": "Antofagasta",
        "shortname": "II",
        "link": "",
        "comment": "",
        "image": "",
        "color_map": "#7798bb",
        "color_map_over": "#366CA3"
    },
    "st3": {
        "id": 3,
        "name": "Arica y Parinacota",
        "shortname": "XV",
        "link": "",
        "comment": "",
        "image": "",
        "color_map": "#7798bb",
        "color_map_over": "#366CA3"
    },
    "st4": {
        "id": 4,
        "name": "Atacama",
        "shortname": "III",
        "link": "",
        "comment": "",
        "image": "",
        "color_map": "#7798bb",
        "color_map_over": "#366CA3"
    },
    "st5": {
        "id": 5,
        "name": "Bío-Bío",
        "shortname": "VIII",
        "link": "",
        "comment": "",
        "image": "",
        "color_map": "#7798bb",
        "color_map_over": "#366CA3"
    },
    "st6": {
        "id": 6,
        "name": "Coquimbo",
        "shortname": "IV",
        "link": "",
        "comment": "",
        "image": "",
        "color_map": "#7798bb",
        "color_map_over": "#366CA3"
    },
    "st7": {
        "id": 7,
        "name": "La Araucanía",
        "shortname": "IX",
        "link": "",
        "comment": "",
        "image": "",
        "color_map": "#7798bb",
        "color_map_over": "#366CA3"
    },
    "st8": {
        "id": 8,
        "name": "Libertador General Bernardo O'Higgins",
        "shortname": "VI",
        "link": "",
        "comment": "",
        "image": "",
        "color_map": "#7798bb",
        "color_map_over": "#366CA3"
    },
    "st9": {
        "id": 9,
        "name": "Los Lagos",
        "shortname": "X",
        "link": "",
        "comment": "",
        "image": "",
        "color_map": "#7798bb",
        "color_map_over": "#366CA3"
    },
    "st10": {
        "id": 10,
        "name": "Los Ríos",
        "shortname": "XIV",
        "link": "",
        "comment": "",
        "image": "",
        "color_map": "#7798bb",
        "color_map_over": "#366CA3"
    },
    "st11": {
        "id": 11,
        "name": "Magallanes y Antártica Chilena",
        "shortname": "XII",
        "link": "",
        "comment": "",
        "image": "",
        "color_map": "#7798bb",
        "color_map_over": "#366CA3"
    },
    "st12": {
        "id": 12,
        "name": "Maule",
        "shortname": "VII",
        "link": "",
        "comment": "",
        "image": "",
        "color_map": "#7798bb",
        "color_map_over": "#366CA3"
    },
    "st13": {
        "id": 13,
        "name": "Ñuble",
        "shortname": "XVI",
        "link": "",
        "comment": "",
        "image": "",
        "color_map": "#7798bb",
        "color_map_over": "#366CA3"
    },
    "st14": {
        "id": 14,
        "name": "Región Metropolitana de Santiago",
        "shortname": "RM",
        "link": "",
        "comment": "",
        "image": "",
        "color_map": "#7798bb",
        "color_map_over": "#366CA3"
    },
    "st15": {
        "id": 15,
        "name": "Tarapacá",
        "shortname": "I",
        "link": "",
        "comment": "",
        "image": "",
        "color_map": "#7798bb",
        "color_map_over": "#366CA3"
    },
    "st16": {
        "id": 16,
        "name": "Valparaíso",
        "shortname": "V",
        "link": "",
        "comment": "",
        "image": "",
        "color_map": "#7798bb",
        "color_map_over": "#366CA3"
    }
}